mobilityapp/__init__.py
mobilityapp/app.py
mobilityapp/supportfunctions.py
mobilityapp/version.py
mobilityapp-0.1.4.dist-info/entry_points.txt
mobilityapp-0.1.4.dist-info/licenses/LICENSE
mobilityapp-0.1.4.dist-info/WHEEL
mobilityapp-0.1.4.dist-info/METADATA
mobilityapp-0.1.4.dist-info/RECORD
