Metadata-Version: 2.4
Name: mobilityapp
Version: 0.1.4
Summary: Python-based tool to analyse conductance vs gate voltage data and extract mobility and density.
Maintainer-email: Damon Carrad <djcarrad@gmail.com>
Classifier: Development Status :: 3 - Alpha
Classifier: Intended Audience :: Science/Research
Classifier: License :: OSI Approved :: MIT License
Classifier: Programming Language :: Python :: 3 :: Only
Classifier: Programming Language :: Python :: 3.10
Classifier: Programming Language :: Python :: 3.11
Classifier: Programming Language :: Python :: 3.12
Classifier: Programming Language :: Python :: 3.13
Classifier: Topic :: Scientific/Engineering
License-File: LICENSE
Requires-Dist: numpy
Requires-Dist: scipy
Requires-Dist: matplotlib
Requires-Dist: ipykernel
Requires-Dist: lmfit
Project-URL: Homepage, https://github.com/djcarrad/MobilityApp
